distclust/__init__.py
distclust/utils.py
distclust-1.0.0.dist-info/licenses/LICENSE.txt
distclust-1.0.0.dist-info/METADATA
distclust-1.0.0.dist-info/WHEEL
distclust-1.0.0.dist-info/top_level.txt
distclust-1.0.0.dist-info/RECORD
