Metadata-Version: 2.4
Name: distclust
Version: 1.0.0
Summary: A package for clustering distributions
Author-email: Mohammadmahdi Ghasemloo <mohammad_ghaselmoo@tamu.edu>, David Eckman <eckman@tamu.edu>
License-Expression: MIT
Classifier: Programming Language :: Python :: 3
Classifier: Operating System :: OS Independent
Requires-Python: >=3.9
License-File: LICENSE.txt
Requires-Dist: numpy
Requires-Dist: scipy
Requires-Dist: pandas
Requires-Dist: scikit-learn
Requires-Dist: matplotlib
Dynamic: license-file
